django_auto_admin_fieldsets/__init__.py
django_auto_admin_fieldsets/admin.py
django_auto_admin_fieldsets-0.2.0.dist-info/METADATA
django_auto_admin_fieldsets-0.2.0.dist-info/WHEEL
django_auto_admin_fieldsets-0.2.0.dist-info/licenses/LICENSE
django_auto_admin_fieldsets-0.2.0.dist-info/RECORD
