Metadata-Version: 2.4
Name: django-auto-admin-fieldsets
Version: 0.2.0
Summary: A Django utility for automatically handling unspecified fields in admin fieldsets
Project-URL: Documentation, https://github.com/matthiask/django-auto-admin-fieldsets#readme
Project-URL: Homepage, https://github.com/matthiask/django-auto-admin-fieldsets
Project-URL: Issues, https://github.com/matthiask/django-auto-admin-fieldsets/issues
Author-email: Matthias Kestenholz <mk@feinheit.ch>
License: MIT
License-File: LICENSE
Keywords: admin,django,fieldsets,utility
Classifier: Development Status :: 4 - Beta
Classifier: Environment :: Web Environment
Classifier: Framework :: Django
Classifier: Framework :: Django :: 4.2
Classifier: Framework :: Django :: 5.0
Classifier: Framework :: Django :: 5.1
Classifier: Framework :: Django :: 5.2
Classifier: Intended Audience :: Developers
Classifier: License :: OSI Approved :: MIT License
Classifier: Operating System :: OS Independent
Classifier: Programming Language :: Python
Classifier: Programming Language :: Python :: 3 :: Only
Classifier: Programming Language :: Python :: 3.10
Classifier: Programming Language :: Python :: 3.11
Classifier: Programming Language :: Python :: 3.12
Classifier: Programming Language :: Python :: 3.13
Classifier: Topic :: Internet :: WWW/HTTP
Classifier: Topic :: Software Development :: Libraries :: Python Modules
Requires-Python: >=3.10
Provides-Extra: tests
Requires-Dist: coverage; extra == 'tests'
